videonoise/__init__.py
videonoise/videonoise.py
videonoise-0.3.dist-info/LICENSE
videonoise-0.3.dist-info/METADATA
videonoise-0.3.dist-info/WHEEL
videonoise-0.3.dist-info/entry_points.txt
videonoise-0.3.dist-info/top_level.txt
videonoise-0.3.dist-info/RECORD
